yelp_encodings/__init__.py
yelp_encodings/internet.py
yelp_encodings/py.typed
yelp_encodings-2.0.0.dist-info/METADATA
yelp_encodings-2.0.0.dist-info/WHEEL
yelp_encodings-2.0.0.dist-info/top_level.txt
yelp_encodings-2.0.0.dist-info/RECORD
