Metadata-Version: 2.1
Name: yelp-encodings
Version: 2.0.0
Summary: string encodings invented and maintained by yelp
Home-page: https://github.com/Yelp/yelp_encodings
Author: Buck Golemon
Author-email: buck@yelp.com
License: UNKNOWN
Platform: any
Classifier: License :: Public Domain
Classifier: Programming Language :: Python :: 3
Classifier: Programming Language :: Python :: 3.7
Requires-Python: >=3.7
Requires-Dist: typing-extensions
